yaml_heritage/__init__.py
yaml_heritage/dict_utils.py
yaml_heritage/generic_types.py
yaml_heritage/heritage.py
yaml_heritage/populate.py
yaml_heritage/utils.py
yaml_heritage/yaml_utils.py
yaml_heritage-0.0.1.dist-info/METADATA
yaml_heritage-0.0.1.dist-info/WHEEL
yaml_heritage-0.0.1.dist-info/top_level.txt
yaml_heritage-0.0.1.dist-info/RECORD
