Metadata-Version: 2.1
Name: yaml-heritage
Version: 0.0.1
Summary: Read YAML file into classes.
Home-page: https://github.com/RemiRousseau/drawable.git
Author: kyrylo-gr
Author-email: cryo.paris.su@gmail.com
License: MIT
Requires-Dist: pyyaml
